gen_reqs/__init__.py
gen_reqs/cli.py
gen_reqs-0.1.0.dist-info/METADATA
gen_reqs-0.1.0.dist-info/WHEEL
gen_reqs-0.1.0.dist-info/entry_points.txt
gen_reqs-0.1.0.dist-info/licenses/LICENSE
gen_reqs-0.1.0.dist-info/RECORD
