Metadata-Version: 2.3
Name: gen-reqs
Version: 0.1.0
Summary: A tool to automatically detect Python project dependencies and generate requirements.txt
Author-email: Jordan Richter <derquerbaer@gmail.com>
License: MIT License
License-File: LICENSE
Requires-Python: >=3.8
